flambe/__init__.py
flambe/const.py
flambe/logo.py
flambe/version.py
flambe/cluster/__init__.py
flambe/cluster/aws.py
flambe/cluster/cluster.py
flambe/cluster/const.py
flambe/cluster/errors.py
flambe/cluster/ssh.py
flambe/cluster/utils.py
flambe/cluster/instance/__init__.py
flambe/cluster/instance/errors.py
flambe/cluster/instance/instance.py
flambe/cluster/instance/scripts/install_cuda_ubuntu1804.sh
flambe/cluster/instance/scripts/install_docker.sh
flambe/cluster/instance/scripts/install_nvidia_docker.sh
flambe/compile/__init__.py
flambe/compile/component.py
flambe/compile/const.py
flambe/compile/downloader.py
flambe/compile/extensions.py
flambe/compile/registrable.py
flambe/compile/serialization.py
flambe/compile/utils.py
flambe/dataset/__init__.py
flambe/dataset/dataset.py
flambe/dataset/tabular.py
flambe/experiment/__init__.py
flambe/experiment/experiment.py
flambe/experiment/options.py
flambe/experiment/progress.py
flambe/experiment/tune_adapter.py
flambe/experiment/utils.py
flambe/experiment/wording.py
flambe/experiment/webapp/__init__.py
flambe/experiment/webapp/app.py
flambe/experiment/webapp/static/ASAPP_Flambe_Logo_RGB_FullColor.svg
flambe/experiment/webapp/static/main.js
flambe/experiment/webapp/templates/console.html
flambe/experiment/webapp/templates/index.html
flambe/export/__init__.py
flambe/export/builder.py
flambe/export/exporter.py
flambe/field/__init__.py
flambe/field/bow.py
flambe/field/field.py
flambe/field/label.py
flambe/field/text.py
flambe/learn/__init__.py
flambe/learn/distillation.py
flambe/learn/eval.py
flambe/learn/script.py
flambe/learn/train.py
flambe/learn/utils.py
flambe/logging/__init__.py
flambe/logging/datatypes.py
flambe/logging/logging.py
flambe/logging/utils.py
flambe/logging/handler/__init__.py
flambe/logging/handler/contextual_file.py
flambe/logging/handler/tensorboard.py
flambe/metric/__init__.py
flambe/metric/metric.py
flambe/metric/dev/__init__.py
flambe/metric/dev/accuracy.py
flambe/metric/dev/auc.py
flambe-0.4.18.dist-info/LICENSE
flambe-0.4.18.dist-info/METADATA
flambe-0.4.18.dist-info/WHEEL
flambe-0.4.18.dist-info/top_level.txt
flambe-0.4.18.dist-info/zip-safe
flambe-0.4.18.dist-info/RECORD
