Metadata-Version: 2.1
Name: flambe
Version: 0.4.18
Summary: Pytorch based library for robust prototyping, standardized                 benchmarking, and effortless experiment management
Home-page: UNKNOWN
Author: ASAPP Inc.
Author-email: flambe@asapp.com
License: UNKNOWN
Platform: UNKNOWN
Requires-Python: >=3.6.1
Requires-Dist: colorama (~=0.3.9)
Requires-Dist: torch (~=1.3.0)
Requires-Dist: numpy (~=1.16.0)
Requires-Dist: ruamel.yaml (<0.16.5,>=0.15.87)
Requires-Dist: pandas (>=0.23.4)
Requires-Dist: tqdm (~=4.28)
Requires-Dist: scikit-learn (~=0.20.3)
Requires-Dist: paramiko (~=2.7.1)
Requires-Dist: boto3 (>=1.9.100)
Requires-Dist: ray (==0.7.6)
Requires-Dist: requests (~=2.21.0)
Requires-Dist: Flask (~=1.0.0)
Requires-Dist: tensorboardx-hparams (==1.7.2)
Requires-Dist: GitPython (~=2.1.11)
Requires-Dist: sru (~=2.2.1)
Requires-Dist: pygments (~=2.3.1)
Requires-Dist: nltk (~=3.4.1)
Requires-Dist: dill (>=0.3.1)
Requires-Dist: gensim (==3.7.3)
Requires-Dist: pip (~=19.1)
Requires-Dist: awscli (~=1.17)
Requires-Dist: transformers (~=2.2.1)
Requires-Dist: jinja2 (~=2.10.1)
Requires-Dist: ninja (~=1.9.0)
